pixivery/__init__.py
pixivery/client.py
pixivery/error.py
pixivery/http.py
pixivery/utils.py
pixivery-1.0.0.dist-info/METADATA
pixivery-1.0.0.dist-info/WHEEL
pixivery-1.0.0.dist-info/top_level.txt
pixivery-1.0.0.dist-info/RECORD
