Metadata-Version: 2.1
Name: pixivery
Version: 1.0.0
Summary: 픽시브(랭킹, 검색) 크롤링 라이브러리
Home-page: https://github.com/VoidAsMad/Pixivery
Author: VoidAsMad
Author-email: voidasmad@gmail.com
License: MIT
Platform: UNKNOWN
Requires-Python: >=3.6
